goes2go/NEW.py
goes2go/__init__.py
goes2go/_version.py
goes2go/accessors.py
goes2go/data.py
goes2go/product_table.txt
goes2go/rgb.py
goes2go/tools.py
goes2go-2025.10.0.dist-info/METADATA
goes2go-2025.10.0.dist-info/WHEEL
goes2go-2025.10.0.dist-info/licenses/LICENSE
goes2go-2025.10.0.dist-info/RECORD
