Metadata-Version: 2.4
Name: goes2go
Version: 2025.10.0
Summary: Retrieve GOES Satellite data from AWS. Also proves some RGB recipes.
Project-URL: Homepage, https://github.com/blaylockbk/goes2go
Project-URL: Documentation, https://goes2go.readthedocs.io/
Project-URL: Repository, https://github.com/blaylockbk/goes2go
Project-URL: Changelog, https://github.com/blaylockbk/goes2go/releases
Project-URL: Bug Tracker, https://github.com/blaylockbk/goes2go/issues
Author-email: "Brian K. Blaylock" <blaylockbk@gmail.com>
Maintainer-email: "Brian K. Blaylock" <blaylockbk@gmail.com>
License: MIT License
License-File: LICENSE
Keywords: AWS,GOES,NOAA,atmosphere,meteorology,satellite,weather,xarray
Classifier: Development Status :: 4 - Beta
Classifier: Intended Audience :: Science/Research
Classifier: License :: OSI Approved :: MIT License
Classifier: Operating System :: MacOS
Classifier: Operating System :: Microsoft :: Windows
Classifier: Operating System :: POSIX :: Linux
Classifier: Programming Language :: Python :: 3
Classifier: Programming Language :: Python :: 3.10
Classifier: Programming Language :: Python :: 3.11
Classifier: Programming Language :: Python :: 3.12
Classifier: Programming Language :: Python :: 3.13
Classifier: Topic :: Scientific/Engineering :: Atmospheric Science
Requires-Python: >=3.10
Requires-Dist: cartopy>=0.24.1
Requires-Dist: h5netcdf>=1.6.1
Requires-Dist: matplotlib>=3.10.1
Requires-Dist: metpy>=1.7.0
Requires-Dist: numpy>=2.2.5
Requires-Dist: pandas>=2.2.3
Requires-Dist: s3fs>=2025.3.2
Requires-Dist: toml>=0.10.2
Requires-Dist: xarray>=2025.4.0
